{
    "project_name":       "esp_oled_25",
    "project_path":       "D:/ESP/workspace/MyProjects/esp_oled_25",
    "build_dir":          "D:/ESP/workspace/MyProjects/esp_oled_25/build",
    "config_file":        "D:/ESP/workspace/MyProjects/esp_oled_25/sdkconfig",
    "config_defaults":    "",
    "app_elf":            "esp_oled_25.elf",
    "app_bin":            "esp_oled_25.bin",
    "git_revision":       "v4.3.1-dirty",
    "target":             "esp32",
    "phy_data_partition": "",
    "monitor_baud" :      "115200",
    "monitor_toolprefix": "xtensa-esp32-elf-",
    "config_environment" : {
        "COMPONENT_KCONFIGS" : "D:/ESP/components/app_trace/Kconfig;D:/ESP/components/asio/Kconfig;D:/ESP/components/bt/Kconfig;D:/ESP/components/coap/Kconfig;D:/ESP/components/driver/Kconfig;D:/ESP/components/efuse/Kconfig;D:/ESP/components/esp-tls/Kconfig;D:/ESP/components/esp32/Kconfig;D:/ESP/components/esp_adc_cal/Kconfig;D:/ESP/components/esp_common/Kconfig;D:/ESP/components/esp_eth/Kconfig;D:/ESP/components/esp_event/Kconfig;D:/ESP/components/esp_gdbstub/Kconfig;D:/ESP/components/esp_http_client/Kconfig;D:/ESP/components/esp_http_server/Kconfig;D:/ESP/components/esp_https_ota/Kconfig;D:/ESP/components/esp_https_server/Kconfig;D:/ESP/components/esp_netif/Kconfig;D:/ESP/components/esp_pm/Kconfig;D:/ESP/components/esp_system/Kconfig;D:/ESP/components/esp_timer/Kconfig;D:/ESP/components/esp_wifi/Kconfig;D:/ESP/components/espcoredump/Kconfig;D:/ESP/components/fatfs/Kconfig;D:/ESP/components/freemodbus/Kconfig;D:/ESP/components/freertos/Kconfig;D:/ESP/components/heap/Kconfig;D:/ESP/components/jsmn/Kconfig;D:/ESP/components/libsodium/Kconfig;D:/ESP/components/log/Kconfig;D:/ESP/components/lwip/Kconfig;D:/ESP/components/mbedtls/Kconfig;D:/ESP/components/mdns/Kconfig;D:/ESP/components/mqtt/Kconfig;D:/ESP/components/newlib/Kconfig;D:/ESP/components/nvs_flash/Kconfig;D:/ESP/components/openssl/Kconfig;D:/ESP/components/pthread/Kconfig;D:/ESP/components/spi_flash/Kconfig;D:/ESP/components/spiffs/Kconfig;D:/ESP/components/tcp_transport/Kconfig;D:/ESP/components/tinyusb/Kconfig;D:/ESP/components/unity/Kconfig;D:/ESP/components/vfs/Kconfig;D:/ESP/components/wear_levelling/Kconfig;D:/ESP/components/wifi_provisioning/Kconfig;D:/ESP/components/wpa_supplicant/Kconfig",
        "COMPONENT_KCONFIGS_PROJBUILD" : "D:/ESP/components/app_update/Kconfig.projbuild;D:/ESP/components/bootloader/Kconfig.projbuild;D:/ESP/components/esptool_py/Kconfig.projbuild;D:/ESP/components/partition_table/Kconfig.projbuild;D:/ESP/workspace/MyProjects/esp_oled_25/core/Kconfig.projbuild"
    },
    "build_components" : [ "app_trace", "app_update", "asio", "bootloader", "bootloader_support", "bt", "cbor", "cmock", "coap", "console", "core", "cxx", "driver", "efuse", "esp-tls", "esp32", "esp_adc_cal", "esp_common", "esp_eth", "esp_event", "esp_gdbstub", "esp_hid", "esp_http_client", "esp_http_server", "esp_https_ota", "esp_https_server", "esp_hw_support", "esp_ipc", "esp_local_ctrl", "esp_netif", "esp_pm", "esp_ringbuf", "esp_rom", "esp_serial_slave_link", "esp_system", "esp_timer", "esp_websocket_client", "esp_wifi", "espcoredump", "esptool_py", "expat", "fatfs", "freemodbus", "freertos", "hal", "heap", "idf_test", "jsmn", "json", "libsodium", "log", "lwip", "mbedtls", "mdns", "mqtt", "newlib", "nghttp", "nvs_flash", "openssl", "partition_table", "perfmon", "protobuf-c", "protocomm", "pthread", "sdmmc", "soc", "spi_flash", "spiffs", "tcp_transport", "tcpip_adapter", "tinyusb", "u8g2", "u8g2-hal-esp-idf", "ulp", "unity", "vfs", "wear_levelling", "wifi_provisioning", "wpa_supplicant", "xtensa", "" ],
    "build_component_paths" : [ "D:/ESP/components/app_trace", "D:/ESP/components/app_update", "D:/ESP/components/asio", "D:/ESP/components/bootloader", "D:/ESP/components/bootloader_support", "D:/ESP/components/bt", "D:/ESP/components/cbor", "D:/ESP/components/cmock", "D:/ESP/components/coap", "D:/ESP/components/console", "D:/ESP/workspace/MyProjects/esp_oled_25/core", "D:/ESP/components/cxx", "D:/ESP/components/driver", "D:/ESP/components/efuse", "D:/ESP/components/esp-tls", "D:/ESP/components/esp32", "D:/ESP/components/esp_adc_cal", "D:/ESP/components/esp_common", "D:/ESP/components/esp_eth", "D:/ESP/components/esp_event", "D:/ESP/components/esp_gdbstub", "D:/ESP/components/esp_hid", "D:/ESP/components/esp_http_client", "D:/ESP/components/esp_http_server", "D:/ESP/components/esp_https_ota", "D:/ESP/components/esp_https_server", "D:/ESP/components/esp_hw_support", "D:/ESP/components/esp_ipc", "D:/ESP/components/esp_local_ctrl", "D:/ESP/components/esp_netif", "D:/ESP/components/esp_pm", "D:/ESP/components/esp_ringbuf", "D:/ESP/components/esp_rom", "D:/ESP/components/esp_serial_slave_link", "D:/ESP/components/esp_system", "D:/ESP/components/esp_timer", "D:/ESP/components/esp_websocket_client", "D:/ESP/components/esp_wifi", "D:/ESP/components/espcoredump", "D:/ESP/components/esptool_py", "D:/ESP/components/expat", "D:/ESP/components/fatfs", "D:/ESP/components/freemodbus", "D:/ESP/components/freertos", "D:/ESP/components/hal", "D:/ESP/components/heap", "D:/ESP/components/idf_test", "D:/ESP/components/jsmn", "D:/ESP/components/json", "D:/ESP/components/libsodium", "D:/ESP/components/log", "D:/ESP/components/lwip", "D:/ESP/components/mbedtls", "D:/ESP/components/mdns", "D:/ESP/components/mqtt", "D:/ESP/components/newlib", "D:/ESP/components/nghttp", "D:/ESP/components/nvs_flash", "D:/ESP/components/openssl", "D:/ESP/components/partition_table", "D:/ESP/components/perfmon", "D:/ESP/components/protobuf-c", "D:/ESP/components/protocomm", "D:/ESP/components/pthread", "D:/ESP/components/sdmmc", "D:/ESP/components/soc", "D:/ESP/components/spi_flash", "D:/ESP/components/spiffs", "D:/ESP/components/tcp_transport", "D:/ESP/components/tcpip_adapter", "D:/ESP/components/tinyusb", "D:/ESP/workspace/MyProjects/esp_oled_25/components/u8g2", "D:/ESP/workspace/MyProjects/esp_oled_25/components/u8g2-hal-esp-idf", "D:/ESP/components/ulp", "D:/ESP/components/unity", "D:/ESP/components/vfs", "D:/ESP/components/wear_levelling", "D:/ESP/components/wifi_provisioning", "D:/ESP/components/wpa_supplicant", "D:/ESP/components/xtensa", "" ]
}
